underthesea/VERSION
underthesea/__init__.py
underthesea/cli.py
underthesea/data_fetcher.py
underthesea/datasets.yaml
underthesea/file_utils.py
underthesea/model_fetcher.py
underthesea/models.yaml
underthesea/agent/__init__.py
underthesea/agent/agent.py
underthesea/agent/default_tools.py
underthesea/agent/llm.py
underthesea/agent/tools.py
underthesea/corpus/__init__.py
underthesea/corpus/categorized_corpus.py
underthesea/corpus/conll_corpus.py
underthesea/corpus/corpus.py
underthesea/corpus/data.py
underthesea/corpus/plaintext_corpus.py
underthesea/corpus/tagged_corpus.py
underthesea/corpus/util.py
underthesea/corpus/uvd.py
underthesea/corpus/validate_corpus.py
underthesea/corpus/word_tokenize_corpus.py
underthesea/corpus/ws_corpus.py
underthesea/corpus/data/Viet11K.txt
underthesea/corpus/data/Viet22K.txt
underthesea/corpus/data/Viet39K.txt
underthesea/corpus/data/Viet74K.txt
underthesea/corpus/readers/__init__.py
underthesea/corpus/readers/dictionary_loader.py
underthesea/datasets/__init__.py
underthesea/datasets/stopwords/__init__.py
underthesea/datasets/stopwords/stopwords.txt
underthesea/datasets/stopwords/stopwords_dev.txt
underthesea/datasets/uit_absa_hotel/uit_absa_hotel.py
underthesea/datasets/uit_absa_restaurant/uit_absa_restaurant.py
underthesea/datasets/uts_dictionary/__init__.py
underthesea/datasets/vlsp2013_pos/__init__.py
underthesea/datasets/vlsp2013_wtk/__init__.py
underthesea/datasets/vlsp2013_wtk/revise_1.py
underthesea/datasets/vlsp2013_wtk/revise_2.py
underthesea/datasets/vlsp2013_wtk/revise_corpus.py
underthesea/datasets/vlsp2013_wtk/validate.py
underthesea/datasets/vlsp2013_wtk/vlsp2013_wtk_r2.py
underthesea/datasets/vlsp2016_sa/__init__.py
underthesea/datasets/vlsp2016_sa/vlsp2016_sa_corpus.py
underthesea/datasets/vlsp2020_dp/__init__.py
underthesea/datasets/vlsp2020_dp/import_corpus.py
underthesea/dictionary/__init__.py
underthesea/feature_engineering/__init__.py
underthesea/feature_engineering/feature.py
underthesea-9.2.1.dist-info/licenses/LICENSE
underthesea-9.2.1.dist-info/METADATA
underthesea-9.2.1.dist-info/WHEEL
underthesea-9.2.1.dist-info/entry_points.txt
underthesea-9.2.1.dist-info/top_level.txt
underthesea-9.2.1.dist-info/RECORD
