Metadata-Version: 2.4
Name: underthesea
Version: 9.2.1
Summary: Vietnamese NLP Toolkit
Author-email: Vu Anh <anhv.ict91@gmail.com>
License-Expression: GPL-3.0
Project-URL: Homepage, https://undertheseanlp.com/
Project-URL: Repository, https://github.com/undertheseanlp/underthesea
Classifier: Development Status :: 5 - Production/Stable
Classifier: Intended Audience :: Developers
Classifier: Intended Audience :: Science/Research
Classifier: Operating System :: POSIX :: Linux
Classifier: Operating System :: MacOS :: MacOS X
Classifier: Operating System :: Microsoft :: Windows
Classifier: Natural Language :: English
Classifier: Programming Language :: Python :: 3
Classifier: Programming Language :: Python :: 3.10
Classifier: Programming Language :: Python :: 3.11
Classifier: Programming Language :: Python :: 3.12
Classifier: Programming Language :: Python :: 3.13
Classifier: Programming Language :: Python :: 3.14
Requires-Python: >=3.10
License-File: LICENSE
Requires-Dist: Click>=6.0
Requires-Dist: python-crfsuite>=0.9.6
Requires-Dist: tqdm
Requires-Dist: requests
Requires-Dist: joblib
Requires-Dist: scikit-learn>=1.6.1
Requires-Dist: PyYAML
Requires-Dist: underthesea_core>=3.0.3
Requires-Dist: huggingface-hub
Provides-Extra: train
Requires-Dist: seqeval; extra == "train"
Provides-Extra: deep
Requires-Dist: torch>=2.0.0; extra == "deep"
Requires-Dist: transformers>=4.30.0; extra == "deep"
Provides-Extra: voice
Requires-Dist: jax>=0.4.25; extra == "voice"
Requires-Dist: jaxlib>=0.4.25; extra == "voice"
Requires-Dist: dm-haiku>=0.0.12; extra == "voice"
Requires-Dist: optax; extra == "voice"
Requires-Dist: soundfile; extra == "voice"
Requires-Dist: matplotlib; extra == "voice"
Requires-Dist: playsound3; extra == "voice"
Provides-Extra: prompt
Requires-Dist: openai; extra == "prompt"
Provides-Extra: agent
Requires-Dist: openai>=2.16.0; extra == "agent"
Provides-Extra: langdetect
Requires-Dist: fasttext; extra == "langdetect"
Provides-Extra: test
Requires-Dist: nose==1.3.7; extra == "test"
Provides-Extra: dev
Requires-Dist: ruff>=0.9.0; extra == "dev"
Requires-Dist: tox; extra == "dev"
Provides-Extra: docs
Requires-Dist: mkdocs>=1.5.0; extra == "docs"
Requires-Dist: mkdocs-material>=9.0.0; extra == "docs"
Requires-Dist: mkdocstrings[python]>=0.24.0; extra == "docs"
Requires-Dist: pymdown-extensions>=10.0; extra == "docs"
Dynamic: license-file
